odoo10_addon_l10n_be_iso20022_pain-10.0.1.0.0.99.dev6-py2.7-nspkg.pth
odoo/addons/l10n_be_iso20022_pain/README.rst
odoo/addons/l10n_be_iso20022_pain/__init__.py
odoo/addons/l10n_be_iso20022_pain/__manifest__.py
odoo/addons/l10n_be_iso20022_pain/i18n/fr.po
odoo/addons/l10n_be_iso20022_pain/i18n/l10n_be_iso20022_pain.pot
odoo/addons/l10n_be_iso20022_pain/models/__init__.py
odoo/addons/l10n_be_iso20022_pain/models/account_move_line.py
odoo/addons/l10n_be_iso20022_pain/models/account_payment_line.py
odoo/addons/l10n_be_iso20022_pain/static/description/icon.png
odoo/addons/l10n_be_iso20022_pain/tests/__init__.py
odoo/addons/l10n_be_iso20022_pain/tests/test_l10n_be_iso20022_pain.py
odoo10_addon_l10n_be_iso20022_pain-10.0.1.0.0.99.dev6.dist-info/METADATA
odoo10_addon_l10n_be_iso20022_pain-10.0.1.0.0.99.dev6.dist-info/RECORD
odoo10_addon_l10n_be_iso20022_pain-10.0.1.0.0.99.dev6.dist-info/WHEEL
odoo10_addon_l10n_be_iso20022_pain-10.0.1.0.0.99.dev6.dist-info/namespace_packages.txt
odoo10_addon_l10n_be_iso20022_pain-10.0.1.0.0.99.dev6.dist-info/top_level.txt
